ksero_payer_rules/__init__.py
ksero_payer_rules/rules.py
ksero_payer_rules/specialy.py
ksero_payer_rules/validation.py
ksero_payer_rules-0.1.1.dist-info/licenses/LICENSE
ksero_payer_rules-0.1.1.dist-info/METADATA
ksero_payer_rules-0.1.1.dist-info/WHEEL
ksero_payer_rules-0.1.1.dist-info/top_level.txt
ksero_payer_rules-0.1.1.dist-info/RECORD
