Metadata-Version: 2.4
Name: ksero-payer-rules
Version: 0.1.1
Summary: Payer-specific rules and validation for insurance card OCR
Home-page: https://github.com/DV1-321/ksero-payer-rules
Author: David Ferguson
Author-email: you@example.com
Classifier: Programming Language :: Python :: 3
Classifier: License :: OSI Approved :: MIT License
Classifier: Intended Audience :: Developers
Classifier: Topic :: Software Development :: Libraries
Requires-Python: >=3.8
License-File: LICENSE
Dynamic: author
Dynamic: author-email
Dynamic: classifier
Dynamic: description
Dynamic: description-content-type
Dynamic: home-page
Dynamic: license-file
Dynamic: requires-python
Dynamic: summary
